woodchopper/__init__.py
woodchopper-2.0.5.dist-info/LICENSE
woodchopper-2.0.5.dist-info/METADATA
woodchopper-2.0.5.dist-info/WHEEL
woodchopper-2.0.5.dist-info/RECORD
