Metadata-Version: 2.3
Name: woodchopper
Version: 2.0.5
Summary: A lightweight logging package
License: LGPL-3.0-only
Author: AfterNoon PM
Author-email: h2o.Drop2010+woodchopper@gmail.com
Requires-Python: >=3.8.1,<4.0.0
Classifier: License :: OSI Approved :: GNU Lesser General Public License v3 (LGPLv3)
Classifier: Programming Language :: Python :: 3
Classifier: Programming Language :: Python :: 3.9
Classifier: Programming Language :: Python :: 3.10
Classifier: Programming Language :: Python :: 3.11
Classifier: Programming Language :: Python :: 3.12
Classifier: Programming Language :: Python :: 3.13
Requires-Dist: rich (>=14.0.0,<15.0.0)
Requires-Dist: spacename (>=1.0.1,<2.0.0)
